bottle_config.py
bottle_config-0.1.2.dist-info/DESCRIPTION.rst
bottle_config-0.1.2.dist-info/METADATA
bottle_config-0.1.2.dist-info/metadata.json
bottle_config-0.1.2.dist-info/RECORD
bottle_config-0.1.2.dist-info/top_level.txt
bottle_config-0.1.2.dist-info/WHEEL
